<?xml version="1.0" encoding="UTF-8"?>
<objects serializationModel="Studio.02.02.00">
	<object class="ParameterPreset" id="{feb87049-4034-4659-bcd5-53af1005233c}">
		<property name="name">
			<value>Cassette1_FastForward</value>
		</property>
		<relationship name="folder">
			<destination>{dd2a58f7-53a3-4a4a-99ed-a1c1598ae3a8}</destination>
		</relationship>
		<relationship name="parameter">
			<destination>{43a4b3ad-256f-4673-a7cc-68a940341256}</destination>
		</relationship>
	</object>
	<object class="GameParameter" id="{43a4b3ad-256f-4673-a7cc-68a940341256}">
		<property name="parameterType">
			<value>1</value>
		</property>
		<property name="maximum">
			<value>2</value>
		</property>
		<property name="isGlobal">
			<value>true</value>
		</property>
		<property name="initialValue">
			<value>0</value>
		</property>
		<property name="isExposedRecursively">
			<value>false</value>
		</property>
	</object>
</objects>
